{"links": [{"source": 57, "target": 61}, {"source": 109, "target": 79}, {"source": 16, "target": 68}, {"source": 69, "target": 43}, {"source": 42, "target": 109}, {"source": 14, "target": 50}, {"source": 70, "target": 32}, {"source": 65, "target": 50}, {"source": 105, "target": 50}, {"source": 39, "target": 30}, {"source": 93, "target": 2}, {"source": 80, "target": 26}, {"source": 32, "target": 68}, {"source": 68, "target": 77}, {"source": 25, "target": 26}, {"source": 57, "target": 75}, {"source": 94, "target": 15}, {"source": 105, "target": 65}, {"source": 67, "target": 32}, {"source": 65, "target": 109}, {"source": 15, "target": 30}, {"source": 23, "target": 2}, {"source": 61, "target": 75}, {"source": 40, "target": 9}, {"source": 15, "target": 11}, {"source": 15, "target": 70}, {"source": 15, "target": 39}, {"source": 2, "target": 79}, {"source": 100, "target": 2}, {"source": 70, "target": 68}, {"source": 15, "target": 77}, {"source": 22, "target": 26}, {"source": 39, "target": 44}, {"source": 2, "target": 43}, {"source": 22, "target": 25}, {"source": 39, "target": 68}, {"source": 11, "target": 56}, {"source": 44, "target": 68}, {"source": 65, "target": 42}, {"source": 30, "target": 77}, {"source": 94, "target": 43}, {"source": 105, "target": 42}, {"source": 44, "target": 32}, {"source": 105, "target": 53}, {"source": 32, "target": 56}, {"source": 39, "target": 56}, {"source": 56, "target": 3}, {"source": 10, "target": 82}, {"source": 80, "target": 22}, {"source": 23, "target": 79}, {"source": 70, "target": 77}, {"source": 80, "target": 25}, {"source": 11, "target": 77}]}