{"links": [{"source": 63, "target": 135}, {"source": 15, "target": 20}, {"source": 36, "target": 44}, {"source": 53, "target": 119}, {"source": 0, "target": 7}, {"source": 96, "target": 146}, {"source": 37, "target": 93}, {"source": 58, "target": 135}, {"source": 81, "target": 179}, {"source": 12, "target": 41}, {"source": 120, "target": 204}, {"source": 56, "target": 65}, {"source": 135, "target": 139}, {"source": 154, "target": 174}, {"source": 66, "target": 123}, {"source": 147, "target": 170}, {"source": 5, "target": 195}, {"source": 146, "target": 235}, {"source": 147, "target": 201}, {"source": 105, "target": 111}, {"source": 167, "target": 173}, {"source": 11, "target": 22}, {"source": 39, "target": 151}, {"source": 76, "target": 229}, {"source": 77, "target": 238}, {"source": 97, "target": 104}, {"source": 47, "target": 93}, {"source": 236, "target": 241}, {"source": 152, "target": 162}, {"source": 24, "target": 151}, {"source": 52, "target": 136}, {"source": 114, "target": 146}, {"source": 13, "target": 20}, {"source": 102, "target": 112}, {"source": 113, "target": 146}, {"source": 153, "target": 157}, {"source": 82, "target": 205}, {"source": 24, "target": 39}, {"source": 6, "target": 70}, {"source": 4, "target": 5}, {"source": 125, "target": 172}, {"source": 76, "target": 228}, {"source": 97, "target": 113}, {"source": 65, "target": 68}, {"source": 144, "target": 220}, {"source": 97, "target": 146}, {"source": 18, "target": 31}, {"source": 99, "target": 146}, {"source": 13, "target": 23}, {"source": 64, "target": 69}, {"source": 87, "target": 239}, {"source": 122, "target": 209}, {"source": 152, "target": 172}, {"source": 59, "target": 72}, {"source": 140, "target": 170}, {"source": 0, "target": 67}, {"source": 97, "target": 107}, {"source": 80, "target": 237}, {"source": 122, "target": 204}, {"source": 58, "target": 121}, {"source": 138, "target": 226}, {"source": 0, "target": 1}, {"source": 149, "target": 212}, {"source": 191, "target": 213}, {"source": 121, "target": 126}, {"source": 158, "target": 201}, {"source": 134, "target": 188}, {"source": 177, "target": 194}, {"source": 69, "target": 109}, {"source": 94, "target": 104}, {"source": 108, "target": 115}, {"source": 58, "target": 66}, {"source": 39, "target": 100}, {"source": 161, "target": 165}, {"source": 57, "target": 65}, {"source": 141, "target": 232}, {"source": 4, "target": 21}, {"source": 155, "target": 162}, {"source": 192, "target": 194}, {"source": 37, "target": 200}, {"source": 95, "target": 97}, {"source": 203, "target": 208}, {"source": 197, "target": 201}, {"source": 124, "target": 127}, {"source": 149, "target": 218}, {"source": 55, "target": 63}, {"source": 32, "target": 35}, {"source": 102, "target": 107}, {"source": 59, "target": 69}, {"source": 36, "target": 46}, {"source": 83, "target": 229}, {"source": 8, "target": 9}, {"source": 15, "target": 43}, {"source": 191, "target": 214}, {"source": 114, "target": 235}, {"source": 140, "target": 147}, {"source": 42, "target": 225}, {"source": 8, "target": 28}, {"source": 127, "target": 212}, {"source": 13, "target": 41}, {"source": 37, "target": 119}, {"source": 127, "target": 209}, {"source": 9, "target": 70}, {"source": 9, "target": 25}, {"source": 207, "target": 218}, {"source": 5, "target": 67}, {"source": 130, "target": 215}, {"source": 63, "target": 121}, {"source": 59, "target": 65}, {"source": 57, "target": 126}, {"source": 58, "target": 116}, {"source": 80, "target": 239}, {"source": 16, "target": 86}, {"source": 12, "target": 13}, {"source": 81, "target": 189}, {"source": 205, "target": 228}, {"source": 118, "target": 218}, {"source": 119, "target": 200}, {"source": 182, "target": 201}, {"source": 13, "target": 16}, {"source": 202, "target": 210}, {"source": 131, "target": 210}, {"source": 41, "target": 100}, {"source": 4, "target": 67}, {"source": 130, "target": 207}, {"source": 223, "target": 227}, {"source": 57, "target": 64}, {"source": 21, "target": 71}, {"source": 14, "target": 151}, {"source": 96, "target": 98}, {"source": 192, "target": 197}, {"source": 56, "target": 62}, {"source": 125, "target": 157}, {"source": 216, "target": 223}, {"source": 57, "target": 63}, {"source": 22, "target": 195}, {"source": 57, "target": 121}, {"source": 0, "target": 71}, {"source": 58, "target": 60}, {"source": 118, "target": 127}, {"source": 1, "target": 19}, {"source": 8, "target": 61}, {"source": 23, "target": 34}, {"source": 104, "target": 231}, {"source": 148, "target": 210}, {"source": 0, "target": 195}, {"source": 183, "target": 201}, {"source": 215, "target": 216}, {"source": 37, "target": 40}, {"source": 135, "target": 137}, {"source": 108, "target": 111}, {"source": 56, "target": 64}, {"source": 6, "target": 71}, {"source": 3, "target": 22}, {"source": 13, "target": 100}, {"source": 48, "target": 189}, {"source": 82, "target": 228}, {"source": 48, "target": 54}, {"source": 128, "target": 177}, {"source": 96, "target": 169}, {"source": 55, "target": 59}, {"source": 60, "target": 121}, {"source": 66, "target": 68}, {"source": 16, "target": 39}, {"source": 170, "target": 232}, {"source": 98, "target": 240}, {"source": 1, "target": 3}, {"source": 116, "target": 121}, {"source": 215, "target": 223}, {"source": 6, "target": 61}, {"source": 120, "target": 124}, {"source": 18, "target": 27}, {"source": 15, "target": 32}, {"source": 116, "target": 126}, {"source": 158, "target": 197}, {"source": 60, "target": 66}, {"source": 84, "target": 199}, {"source": 31, "target": 151}, {"source": 90, "target": 241}, {"source": 91, "target": 229}, {"source": 67, "target": 71}, {"source": 155, "target": 173}, {"source": 46, "target": 136}, {"source": 44, "target": 136}, {"source": 50, "target": 119}, {"source": 58, "target": 63}, {"source": 99, "target": 113}, {"source": 20, "target": 151}, {"source": 130, "target": 220}, {"source": 93, "target": 200}, {"source": 65, "target": 109}, {"source": 96, "target": 115}, {"source": 83, "target": 228}, {"source": 66, "target": 116}, {"source": 78, "target": 230}, {"source": 186, "target": 191}, {"source": 111, "target": 146}, {"source": 137, "target": 139}, {"source": 24, "target": 34}, {"source": 4, "target": 195}, {"source": 97, "target": 231}, {"source": 47, "target": 48}, {"source": 142, "target": 215}, {"source": 27, "target": 32}, {"source": 7, "target": 67}, {"source": 169, "target": 240}, {"source": 45, "target": 136}, {"source": 199, "target": 217}, {"source": 16, "target": 30}, {"source": 141, "target": 143}, {"source": 140, "target": 143}, {"source": 88, "target": 90}, {"source": 126, "target": 139}, {"source": 12, "target": 100}, {"source": 66, "target": 121}, {"source": 15, "target": 41}, {"source": 142, "target": 223}, {"source": 5, "target": 19}, {"source": 108, "target": 169}, {"source": 39, "target": 86}, {"source": 183, "target": 210}, {"source": 13, "target": 43}, {"source": 95, "target": 108}, {"source": 76, "target": 79}, {"source": 57, "target": 139}, {"source": 133, "target": 197}, {"source": 59, "target": 135}, {"source": 131, "target": 202}, {"source": 117, "target": 222}, {"source": 57, "target": 109}, {"source": 32, "target": 43}, {"source": 57, "target": 123}, {"source": 123, "target": 139}, {"source": 99, "target": 112}, {"source": 8, "target": 70}, {"source": 13, "target": 31}, {"source": 34, "target": 100}, {"source": 92, "target": 142}, {"source": 56, "target": 126}, {"source": 58, "target": 109}, {"source": 55, "target": 58}, {"source": 0, "target": 22}, {"source": 5, "target": 6}, {"source": 187, "target": 217}, {"source": 133, "target": 147}, {"source": 104, "target": 105}, {"source": 100, "target": 151}, {"source": 148, "target": 188}, {"source": 107, "target": 110}, {"source": 61, "target": 67}, {"source": 59, "target": 63}, {"source": 0, "target": 3}, {"source": 16, "target": 24}, {"source": 155, "target": 157}, {"source": 59, "target": 137}, {"source": 132, "target": 170}, {"source": 121, "target": 139}, {"source": 50, "target": 51}, {"source": 74, "target": 241}, {"source": 18, "target": 34}, {"source": 109, "target": 121}, {"source": 147, "target": 183}, {"source": 18, "target": 100}, {"source": 68, "target": 139}, {"source": 154, "target": 172}, {"source": 184, "target": 185}, {"source": 65, "target": 69}, {"source": 24, "target": 31}, {"source": 23, "target": 43}, {"source": 121, "target": 183}, {"source": 16, "target": 18}, {"source": 105, "target": 231}, {"source": 61, "target": 70}, {"source": 13, "target": 15}, {"source": 31, "target": 39}, {"source": 13, "target": 24}, {"source": 170, "target": 202}, {"source": 17, "target": 32}, {"source": 64, "target": 109}, {"source": 120, "target": 122}, {"source": 80, "target": 87}, {"source": 18, "target": 39}, {"source": 74, "target": 88}, {"source": 58, "target": 69}, {"source": 20, "target": 41}, {"source": 3, "target": 19}, {"source": 108, "target": 235}, {"source": 83, "target": 205}, {"source": 31, "target": 43}, {"source": 140, "target": 232}, {"source": 64, "target": 65}, {"source": 34, "target": 151}, {"source": 20, "target": 23}, {"source": 13, "target": 151}, {"source": 183, "target": 202}, {"source": 16, "target": 31}, {"source": 31, "target": 100}, {"source": 153, "target": 165}, {"source": 130, "target": 149}, {"source": 36, "target": 136}, {"source": 83, "target": 91}, {"source": 218, "target": 226}, {"source": 36, "target": 45}, {"source": 162, "target": 173}, {"source": 3, "target": 9}, {"source": 37, "target": 81}, {"source": 1, "target": 61}, {"source": 24, "target": 32}, {"source": 141, "target": 170}, {"source": 28, "target": 70}, {"source": 125, "target": 155}]}