{"links": [{"source": 22, "target": 57}, {"source": 6, "target": 185}, {"source": 103, "target": 107}, {"source": 54, "target": 55}, {"source": 57, "target": 163}, {"source": 59, "target": 131}, {"source": 74, "target": 94}, {"source": 13, "target": 131}, {"source": 152, "target": 250}, {"source": 115, "target": 227}, {"source": 256, "target": 260}, {"source": 1, "target": 191}, {"source": 154, "target": 277}, {"source": 59, "target": 97}, {"source": 293, "target": 307}, {"source": 270, "target": 271}, {"source": 11, "target": 83}, {"source": 164, "target": 253}, {"source": 31, "target": 200}, {"source": 27, "target": 248}, {"source": 123, "target": 167}, {"source": 86, "target": 152}, {"source": 48, "target": 159}, {"source": 50, "target": 177}, {"source": 21, "target": 68}, {"source": 98, "target": 227}, {"source": 25, "target": 129}, {"source": 41, "target": 127}, {"source": 22, "target": 148}, {"source": 140, "target": 238}, {"source": 141, "target": 277}, {"source": 111, "target": 136}, {"source": 71, "target": 131}, {"source": 31, "target": 70}, {"source": 309, "target": 311}, {"source": 289, "target": 305}, {"source": 151, "target": 309}, {"source": 45, "target": 285}, {"source": 145, "target": 186}, {"source": 224, "target": 258}, {"source": 31, "target": 138}, {"source": 1, "target": 163}, {"source": 159, "target": 200}, {"source": 38, "target": 97}, {"source": 15, "target": 161}, {"source": 209, "target": 258}, {"source": 2, "target": 86}, {"source": 4, "target": 63}, {"source": 148, "target": 259}, {"source": 4, "target": 69}, {"source": 10, "target": 48}, {"source": 11, "target": 19}, {"source": 33, "target": 98}, {"source": 36, "target": 146}, {"source": 292, "target": 303}, {"source": 219, "target": 305}, {"source": 301, "target": 320}, {"source": 294, "target": 301}, {"source": 313, "target": 323}, {"source": 39, "target": 64}, {"source": 54, "target": 56}, {"source": 9, "target": 60}, {"source": 4, "target": 272}, {"source": 93, "target": 182}, {"source": 41, "target": 63}, {"source": 201, "target": 281}, {"source": 70, "target": 160}, {"source": 317, "target": 320}, {"source": 294, "target": 322}, {"source": 1, "target": 294}, {"source": 1, "target": 52}, {"source": 292, "target": 316}, {"source": 4, "target": 136}, {"source": 28, "target": 278}, {"source": 170, "target": 248}, {"source": 99, "target": 105}, {"source": 39, "target": 220}, {"source": 88, "target": 267}, {"source": 291, "target": 293}, {"source": 301, "target": 322}, {"source": 203, "target": 235}, {"source": 142, "target": 217}, {"source": 94, "target": 182}, {"source": 14, "target": 129}, {"source": 38, "target": 59}, {"source": 56, "target": 256}, {"source": 127, "target": 272}, {"source": 99, "target": 136}, {"source": 273, "target": 287}, {"source": 136, "target": 242}, {"source": 68, "target": 99}, {"source": 48, "target": 70}, {"source": 38, "target": 201}, {"source": 1, "target": 217}, {"source": 81, "target": 103}, {"source": 102, "target": 106}, {"source": 132, "target": 315}, {"source": 79, "target": 92}, {"source": 60, "target": 148}, {"source": 70, "target": 248}, {"source": 223, "target": 256}, {"source": 182, "target": 212}, {"source": 29, "target": 199}, {"source": 143, "target": 248}, {"source": 99, "target": 276}, {"source": 109, "target": 135}, {"source": 296, "target": 316}, {"source": 158, "target": 179}, {"source": 182, "target": 224}, {"source": 90, "target": 146}, {"source": 258, "target": 304}, {"source": 131, "target": 259}, {"source": 133, "target": 153}, {"source": 143, "target": 170}, {"source": 105, "target": 235}, {"source": 240, "target": 275}, {"source": 101, "target": 200}, {"source": 152, "target": 317}, {"source": 107, "target": 136}, {"source": 15, "target": 29}, {"source": 45, "target": 157}, {"source": 162, "target": 258}, {"source": 126, "target": 263}, {"source": 90, "target": 157}, {"source": 73, "target": 227}, {"source": 115, "target": 143}, {"source": 181, "target": 229}, {"source": 13, "target": 104}, {"source": 5, "target": 27}, {"source": 70, "target": 91}, {"source": 109, "target": 180}, {"source": 44, "target": 143}, {"source": 201, "target": 309}, {"source": 81, "target": 107}, {"source": 303, "target": 320}, {"source": 1, "target": 126}, {"source": 33, "target": 121}, {"source": 11, "target": 133}, {"source": 57, "target": 85}, {"source": 307, "target": 309}, {"source": 294, "target": 316}, {"source": 45, "target": 100}, {"source": 301, "target": 303}, {"source": 66, "target": 235}, {"source": 99, "target": 107}, {"source": 31, "target": 63}, {"source": 238, "target": 317}, {"source": 117, "target": 142}, {"source": 52, "target": 117}, {"source": 105, "target": 136}, {"source": 182, "target": 233}, {"source": 299, "target": 317}, {"source": 133, "target": 148}, {"source": 22, "target": 264}, {"source": 86, "target": 156}, {"source": 5, "target": 252}, {"source": 92, "target": 115}, {"source": 3, "target": 15}, {"source": 94, "target": 224}, {"source": 123, "target": 148}, {"source": 320, "target": 323}, {"source": 12, "target": 93}, {"source": 170, "target": 177}, {"source": 200, "target": 274}, {"source": 28, "target": 64}, {"source": 11, "target": 56}, {"source": 137, "target": 218}, {"source": 164, "target": 273}, {"source": 11, "target": 74}, {"source": 11, "target": 256}, {"source": 54, "target": 233}, {"source": 5, "target": 143}, {"source": 73, "target": 248}, {"source": 22, "target": 163}, {"source": 87, "target": 200}, {"source": 104, "target": 108}, {"source": 314, "target": 317}, {"source": 22, "target": 133}, {"source": 152, "target": 281}, {"source": 131, "target": 146}, {"source": 13, "target": 71}, {"source": 99, "target": 204}, {"source": 167, "target": 282}, {"source": 2, "target": 268}, {"source": 50, "target": 274}, {"source": 106, "target": 183}, {"source": 103, "target": 200}, {"source": 56, "target": 74}, {"source": 46, "target": 167}, {"source": 316, "target": 323}, {"source": 21, "target": 159}, {"source": 305, "target": 317}, {"source": 301, "target": 308}, {"source": 107, "target": 313}, {"source": 9, "target": 276}, {"source": 28, "target": 145}, {"source": 11, "target": 54}, {"source": 54, "target": 137}, {"source": 259, "target": 275}, {"source": 228, "target": 259}, {"source": 3, "target": 199}, {"source": 98, "target": 174}, {"source": 11, "target": 12}, {"source": 97, "target": 131}, {"source": 163, "target": 191}, {"source": 146, "target": 157}, {"source": 45, "target": 72}, {"source": 307, "target": 311}, {"source": 50, "target": 138}, {"source": 63, "target": 200}, {"source": 3, "target": 276}, {"source": 185, "target": 211}, {"source": 186, "target": 195}, {"source": 55, "target": 256}, {"source": 108, "target": 266}, {"source": 128, "target": 172}, {"source": 60, "target": 153}, {"source": 19, "target": 267}, {"source": 302, "target": 317}, {"source": 64, "target": 220}, {"source": 232, "target": 248}, {"source": 28, "target": 220}, {"source": 128, "target": 129}, {"source": 14, "target": 209}, {"source": 10, "target": 70}, {"source": 174, "target": 248}, {"source": 34, "target": 179}, {"source": 74, "target": 233}, {"source": 9, "target": 52}, {"source": 4, "target": 68}, {"source": 31, "target": 272}, {"source": 152, "target": 314}, {"source": 22, "target": 85}, {"source": 292, "target": 320}, {"source": 117, "target": 217}, {"source": 94, "target": 233}, {"source": 22, "target": 183}, {"source": 214, "target": 271}, {"source": 29, "target": 220}, {"source": 115, "target": 174}, {"source": 1, "target": 60}, {"source": 292, "target": 308}, {"source": 85, "target": 183}, {"source": 281, "target": 326}, {"source": 11, "target": 93}, {"source": 106, "target": 129}, {"source": 29, "target": 313}, {"source": 105, "target": 111}, {"source": 60, "target": 133}, {"source": 104, "target": 131}, {"source": 203, "target": 284}, {"source": 12, "target": 294}, {"source": 140, "target": 267}, {"source": 20, "target": 59}, {"source": 68, "target": 242}, {"source": 14, "target": 82}, {"source": 90, "target": 131}, {"source": 113, "target": 300}, {"source": 127, "target": 249}, {"source": 27, "target": 92}, {"source": 54, "target": 256}, {"source": 34, "target": 145}, {"source": 79, "target": 177}, {"source": 92, "target": 159}, {"source": 148, "target": 153}, {"source": 9, "target": 129}, {"source": 301, "target": 323}, {"source": 71, "target": 97}, {"source": 19, "target": 260}, {"source": 224, "target": 304}, {"source": 11, "target": 14}, {"source": 33, "target": 87}, {"source": 95, "target": 214}, {"source": 70, "target": 86}, {"source": 99, "target": 111}, {"source": 182, "target": 258}, {"source": 85, "target": 163}, {"source": 127, "target": 204}, {"source": 101, "target": 159}, {"source": 50, "target": 252}, {"source": 123, "target": 191}, {"source": 135, "target": 150}, {"source": 152, "target": 201}, {"source": 108, "target": 239}, {"source": 299, "target": 305}, {"source": 2, "target": 284}, {"source": 4, "target": 101}, {"source": 10, "target": 245}, {"source": 11, "target": 148}, {"source": 77, "target": 276}, {"source": 81, "target": 200}, {"source": 57, "target": 68}, {"source": 185, "target": 218}, {"source": 19, "target": 300}, {"source": 190, "target": 242}, {"source": 36, "target": 38}, {"source": 129, "target": 183}, {"source": 12, "target": 137}, {"source": 19, "target": 113}, {"source": 46, "target": 123}, {"source": 38, "target": 52}, {"source": 57, "target": 129}, {"source": 15, "target": 18}, {"source": 28, "target": 122}, {"source": 27, "target": 29}, {"source": 1, "target": 129}, {"source": 70, "target": 174}, {"source": 57, "target": 107}, {"source": 11, "target": 260}, {"source": 94, "target": 133}, {"source": 112, "target": 326}, {"source": 38, "target": 316}, {"source": 293, "target": 301}, {"source": 82, "target": 209}, {"source": 9, "target": 119}, {"source": 316, "target": 320}, {"source": 63, "target": 99}, {"source": 71, "target": 104}, {"source": 54, "target": 182}, {"source": 303, "target": 321}, {"source": 31, "target": 204}, {"source": 74, "target": 93}, {"source": 70, "target": 143}, {"source": 12, "target": 54}, {"source": 39, "target": 46}, {"source": 162, "target": 201}, {"source": 68, "target": 200}, {"source": 124, "target": 265}, {"source": 115, "target": 274}, {"source": 12, "target": 133}, {"source": 44, "target": 115}, {"source": 36, "target": 259}, {"source": 74, "target": 182}, {"source": 136, "target": 204}, {"source": 48, "target": 284}, {"source": 97, "target": 104}, {"source": 12, "target": 94}, {"source": 15, "target": 205}, {"source": 164, "target": 172}, {"source": 209, "target": 219}, {"source": 107, "target": 242}, {"source": 30, "target": 143}, {"source": 34, "target": 107}, {"source": 117, "target": 253}, {"source": 41, "target": 124}, {"source": 3, "target": 18}, {"source": 308, "target": 316}, {"source": 1, "target": 38}, {"source": 4, "target": 21}, {"source": 64, "target": 278}, {"source": 135, "target": 250}, {"source": 94, "target": 148}, {"source": 141, "target": 154}, {"source": 291, "target": 307}, {"source": 28, "target": 216}, {"source": 137, "target": 219}, {"source": 12, "target": 219}, {"source": 1, "target": 142}, {"source": 162, "target": 260}, {"source": 10, "target": 91}, {"source": 5, "target": 119}, {"source": 38, "target": 239}, {"source": 68, "target": 107}, {"source": 72, "target": 110}, {"source": 68, "target": 136}, {"source": 175, "target": 220}, {"source": 36, "target": 90}, {"source": 301, "target": 316}, {"source": 238, "target": 250}, {"source": 176, "target": 309}, {"source": 202, "target": 264}, {"source": 176, "target": 267}, {"source": 309, "target": 317}, {"source": 21, "target": 105}, {"source": 181, "target": 208}, {"source": 52, "target": 142}, {"source": 44, "target": 227}, {"source": 36, "target": 157}, {"source": 179, "target": 248}, {"source": 316, "target": 322}, {"source": 293, "target": 309}, {"source": 39, "target": 273}, {"source": 160, "target": 265}, {"source": 303, "target": 323}, {"source": 129, "target": 142}, {"source": 103, "target": 274}, {"source": 63, "target": 81}, {"source": 264, "target": 285}, {"source": 102, "target": 216}, {"source": 265, "target": 280}, {"source": 293, "target": 323}, {"source": 19, "target": 233}, {"source": 3, "target": 99}, {"source": 12, "target": 217}, {"source": 209, "target": 224}, {"source": 145, "target": 278}, {"source": 1, "target": 9}, {"source": 127, "target": 276}, {"source": 9, "target": 217}, {"source": 159, "target": 193}, {"source": 59, "target": 90}, {"source": 52, "target": 217}, {"source": 38, "target": 104}, {"source": 220, "target": 298}, {"source": 29, "target": 276}, {"source": 97, "target": 201}, {"source": 92, "target": 177}, {"source": 31, "target": 68}, {"source": 253, "target": 287}, {"source": 143, "target": 288}, {"source": 95, "target": 271}, {"source": 21, "target": 101}, {"source": 154, "target": 210}, {"source": 14, "target": 219}, {"source": 126, "target": 129}, {"source": 160, "target": 245}, {"source": 138, "target": 177}, {"source": 121, "target": 248}, {"source": 21, "target": 41}, {"source": 143, "target": 174}, {"source": 113, "target": 132}, {"source": 219, "target": 224}, {"source": 291, "target": 303}, {"source": 9, "target": 142}, {"source": 27, "target": 79}, {"source": 291, "target": 309}, {"source": 4, "target": 204}, {"source": 12, "target": 60}, {"source": 56, "target": 213}, {"source": 199, "target": 276}, {"source": 156, "target": 201}, {"source": 113, "target": 321}, {"source": 292, "target": 301}, {"source": 33, "target": 70}, {"source": 3, "target": 29}, {"source": 109, "target": 171}]}