{"links": [{"source": 233, "target": 256}, {"source": 110, "target": 120}, {"source": 12, "target": 304}, {"source": 54, "target": 213}, {"source": 80, "target": 81}, {"source": 116, "target": 250}, {"source": 312, "target": 317}, {"source": 209, "target": 256}, {"source": 12, "target": 83}, {"source": 301, "target": 317}, {"source": 99, "target": 125}, {"source": 38, "target": 228}, {"source": 116, "target": 180}, {"source": 108, "target": 191}, {"source": 126, "target": 263}, {"source": 164, "target": 253}, {"source": 63, "target": 251}, {"source": 171, "target": 180}, {"source": 75, "target": 217}, {"source": 48, "target": 159}, {"source": 180, "target": 213}, {"source": 113, "target": 317}, {"source": 223, "target": 304}, {"source": 19, "target": 256}, {"source": 209, "target": 213}, {"source": 296, "target": 317}, {"source": 19, "target": 54}, {"source": 171, "target": 213}, {"source": 225, "target": 256}, {"source": 201, "target": 295}, {"source": 120, "target": 202}, {"source": 309, "target": 311}, {"source": 66, "target": 235}, {"source": 99, "target": 107}, {"source": 110, "target": 264}, {"source": 202, "target": 264}, {"source": 120, "target": 264}, {"source": 46, "target": 240}, {"source": 46, "target": 108}, {"source": 54, "target": 256}, {"source": 12, "target": 213}, {"source": 292, "target": 298}, {"source": 25, "target": 287}, {"source": 39, "target": 273}, {"source": 78, "target": 201}, {"source": 145, "target": 174}, {"source": 142, "target": 278}, {"source": 213, "target": 256}, {"source": 42, "target": 106}, {"source": 54, "target": 304}, {"source": 63, "target": 81}, {"source": 213, "target": 223}, {"source": 21, "target": 48}, {"source": 71, "target": 259}, {"source": 302, "target": 309}, {"source": 46, "target": 133}, {"source": 289, "target": 295}, {"source": 54, "target": 233}, {"source": 110, "target": 202}, {"source": 22, "target": 163}, {"source": 31, "target": 235}, {"source": 9, "target": 85}, {"source": 108, "target": 133}, {"source": 12, "target": 209}, {"source": 24, "target": 65}, {"source": 292, "target": 316}, {"source": 108, "target": 123}, {"source": 203, "target": 265}, {"source": 185, "target": 218}, {"source": 201, "target": 299}, {"source": 35, "target": 252}, {"source": 48, "target": 79}, {"source": 123, "target": 133}, {"source": 12, "target": 93}, {"source": 64, "target": 286}, {"source": 79, "target": 92}, {"source": 112, "target": 267}, {"source": 296, "target": 312}, {"source": 129, "target": 183}, {"source": 20, "target": 97}, {"source": 46, "target": 123}, {"source": 21, "target": 159}, {"source": 320, "target": 324}, {"source": 40, "target": 81}, {"source": 40, "target": 251}, {"source": 63, "target": 80}, {"source": 228, "target": 259}, {"source": 27, "target": 35}, {"source": 300, "target": 321}, {"source": 201, "target": 289}, {"source": 277, "target": 278}, {"source": 107, "target": 125}, {"source": 14, "target": 219}, {"source": 256, "target": 304}, {"source": 213, "target": 304}, {"source": 14, "target": 206}, {"source": 51, "target": 64}, {"source": 12, "target": 233}, {"source": 194, "target": 196}]}