{"links": [{"source": 2, "target": 326}, {"source": 245, "target": 186}, {"source": 327, "target": 186}, {"source": 292, "target": 324}, {"source": 2, "target": 290}, {"source": 245, "target": 327}, {"source": 245, "target": 26}, {"source": 56, "target": 263}, {"source": 178, "target": 46}, {"source": 292, "target": 53}, {"source": 290, "target": 292}, {"source": 326, "target": 46}, {"source": 245, "target": 46}, {"source": 326, "target": 324}, {"source": 327, "target": 99}, {"source": 301, "target": 228}, {"source": 178, "target": 186}, {"source": 26, "target": 46}, {"source": 290, "target": 99}, {"source": 326, "target": 36}, {"source": 2, "target": 178}, {"source": 290, "target": 245}, {"source": 254, "target": 56}, {"source": 39, "target": 254}, {"source": 292, "target": 204}, {"source": 2, "target": 99}, {"source": 326, "target": 186}, {"source": 53, "target": 46}, {"source": 327, "target": 204}, {"source": 2, "target": 245}, {"source": 36, "target": 46}, {"source": 326, "target": 99}, {"source": 292, "target": 26}, {"source": 245, "target": 36}, {"source": 324, "target": 204}, {"source": 99, "target": 46}, {"source": 2, "target": 327}, {"source": 292, "target": 186}, {"source": 301, "target": 264}, {"source": 237, "target": 301}, {"source": 26, "target": 99}, {"source": 46, "target": 204}, {"source": 2, "target": 204}, {"source": 324, "target": 99}, {"source": 326, "target": 204}, {"source": 53, "target": 327}, {"source": 2, "target": 292}, {"source": 290, "target": 186}, {"source": 327, "target": 46}, {"source": 129, "target": 345}, {"source": 228, "target": 264}, {"source": 338, "target": 184}, {"source": 326, "target": 245}, {"source": 292, "target": 99}, {"source": 26, "target": 327}, {"source": 237, "target": 180}, {"source": 26, "target": 204}, {"source": 324, "target": 327}, {"source": 36, "target": 324}, {"source": 178, "target": 53}, {"source": 290, "target": 46}, {"source": 245, "target": 178}, {"source": 326, "target": 53}, {"source": 290, "target": 324}, {"source": 180, "target": 264}, {"source": 301, "target": 180}, {"source": 290, "target": 36}, {"source": 290, "target": 327}, {"source": 53, "target": 186}, {"source": 36, "target": 327}, {"source": 46, "target": 186}, {"source": 245, "target": 204}, {"source": 326, "target": 292}, {"source": 326, "target": 178}, {"source": 292, "target": 36}, {"source": 39, "target": 56}, {"source": 324, "target": 46}, {"source": 2, "target": 324}, {"source": 36, "target": 204}, {"source": 290, "target": 204}, {"source": 237, "target": 264}, {"source": 2, "target": 186}, {"source": 99, "target": 204}, {"source": 237, "target": 228}, {"source": 73, "target": 342}, {"source": 292, "target": 46}, {"source": 36, "target": 26}, {"source": 245, "target": 292}, {"source": 326, "target": 26}, {"source": 2, "target": 26}, {"source": 326, "target": 327}, {"source": 290, "target": 53}, {"source": 39, "target": 263}, {"source": 324, "target": 26}, {"source": 326, "target": 290}, {"source": 2, "target": 46}, {"source": 2, "target": 53}, {"source": 290, "target": 26}, {"source": 168, "target": 280}, {"source": 245, "target": 53}, {"source": 290, "target": 178}, {"source": 178, "target": 292}, {"source": 178, "target": 327}, {"source": 228, "target": 180}, {"source": 254, "target": 263}, {"source": 2, "target": 36}, {"source": 292, "target": 327}, {"source": 245, "target": 99}, {"source": 245, "target": 324}, {"source": 36, "target": 99}]}