{"links": [{"source": 1, "target": 34}, {"source": 138, "target": 145}, {"source": 42, "target": 71}, {"source": 152, "target": 165}, {"source": 46, "target": 61}, {"source": 18, "target": 56}, {"source": 61, "target": 118}, {"source": 7, "target": 68}, {"source": 164, "target": 165}, {"source": 104, "target": 125}, {"source": 163, "target": 164}, {"source": 25, "target": 60}, {"source": 53, "target": 62}, {"source": 125, "target": 129}, {"source": 155, "target": 168}, {"source": 64, "target": 72}, {"source": 60, "target": 62}, {"source": 18, "target": 51}, {"source": 94, "target": 114}, {"source": 88, "target": 138}, {"source": 168, "target": 173}, {"source": 99, "target": 119}, {"source": 21, "target": 68}, {"source": 160, "target": 165}, {"source": 163, "target": 179}, {"source": 119, "target": 122}, {"source": 29, "target": 49}, {"source": 93, "target": 103}, {"source": 39, "target": 58}, {"source": 95, "target": 100}, {"source": 34, "target": 53}, {"source": 30, "target": 61}, {"source": 163, "target": 168}, {"source": 0, "target": 11}, {"source": 25, "target": 53}, {"source": 119, "target": 121}, {"source": 165, "target": 173}, {"source": 89, "target": 146}, {"source": 51, "target": 56}, {"source": 25, "target": 37}, {"source": 122, "target": 125}, {"source": 53, "target": 61}, {"source": 18, "target": 58}, {"source": 164, "target": 173}, {"source": 39, "target": 51}, {"source": 149, "target": 164}, {"source": 25, "target": 62}, {"source": 93, "target": 120}, {"source": 61, "target": 62}, {"source": 103, "target": 127}, {"source": 155, "target": 165}, {"source": 63, "target": 75}, {"source": 49, "target": 53}, {"source": 49, "target": 65}, {"source": 11, "target": 96}, {"source": 112, "target": 126}, {"source": 62, "target": 70}, {"source": 155, "target": 160}, {"source": 58, "target": 56}, {"source": 160, "target": 163}, {"source": 42, "target": 60}, {"source": 37, "target": 62}, {"source": 93, "target": 124}, {"source": 95, "target": 105}, {"source": 37, "target": 70}, {"source": 99, "target": 127}, {"source": 163, "target": 166}, {"source": 46, "target": 60}, {"source": 23, "target": 74}, {"source": 37, "target": 49}, {"source": 149, "target": 163}, {"source": 45, "target": 49}, {"source": 7, "target": 29}, {"source": 163, "target": 165}, {"source": 25, "target": 61}, {"source": 57, "target": 129}, {"source": 18, "target": 39}, {"source": 112, "target": 117}, {"source": 118, "target": 125}, {"source": 25, "target": 34}, {"source": 155, "target": 163}, {"source": 95, "target": 102}, {"source": 164, "target": 179}, {"source": 11, "target": 115}, {"source": 29, "target": 62}, {"source": 42, "target": 61}, {"source": 103, "target": 119}]}